tests/__init__.py
tests/test_transip.py
tests/test_utils.py
tests/utils.py
tests/fixtures/account.json
tests/fixtures/auth.json
tests/fixtures/colocations.json
tests/fixtures/domains.json
tests/fixtures/general.json
tests/services/__init__.py
tests/services/test_api_test.py
tests/services/test_colocations.py
tests/services/test_domains.py
tests/services/test_invoices.py
tests/services/test_products.py
tests/services/test_ssh_keys.py
transip/__init__.py
transip/base.py
transip/exceptions.py
transip/mixins.py
transip/utils.py
transip/v6/__init__.py
transip/v6/objects.py
python_transip-0.6.0.dist-info/COPYING
python_transip-0.6.0.dist-info/COPYING.LESSER
python_transip-0.6.0.dist-info/METADATA
python_transip-0.6.0.dist-info/WHEEL
python_transip-0.6.0.dist-info/top_level.txt
python_transip-0.6.0.dist-info/RECORD
