Metadata-Version: 2.1
Name: python-transip
Version: 0.6.0
Summary: Wrapper for the TransIP API
Home-page: https://github.com/roaldnefs/python-transip
Author: Roald Nefs
Author-email: info@roaldnefs.com
License: LGPLv3
Platform: UNKNOWN
Classifier: Development Status :: 5 - Production/Stable
Classifier: Intended Audience :: Developers
Classifier: Intended Audience :: System Administrators
Classifier: License :: OSI Approved :: GNU Lesser General Public License v3 (LGPLv3)
Classifier: Programming Language :: Python
Classifier: Programming Language :: Python :: 3
Classifier: Programming Language :: Python :: 3.6
Classifier: Programming Language :: Python :: 3.7
Classifier: Programming Language :: Python :: 3.8
Classifier: Programming Language :: Python :: 3.9
Classifier: Programming Language :: Python :: 3.10
Requires-Python: >=3.6
License-File: COPYING
License-File: COPYING.LESSER
Requires-Dist: cryptography (>=3.3.1)
Requires-Dist: requests (>=2.25.1)
